ringbellerpythonapi/__init__.py
ringbellerpythonapi/ringbellerpythonapi.py
ringbellerpythonapi/src/makefile
ringbellerpythonapi/src/lib/libmodemwrapper.so
ringbellerpythonapi/src/modem/makefile
ringbellerpythonapi/src/modem/inc/EC25.h
ringbellerpythonapi/src/modem/inc/audio.h
ringbellerpythonapi/src/modem/inc/comms.h
ringbellerpythonapi/src/modem/inc/hardware.h
ringbellerpythonapi/src/modem/inc/log.h
ringbellerpythonapi/src/modem/inc/modem.h
ringbellerpythonapi/src/modem/inc/utils.h
ringbellerpythonapi/src/modem/src/audio.cpp
ringbellerpythonapi/src/modem/src/comms.cpp
ringbellerpythonapi/src/modem/src/hardware.cpp
ringbellerpythonapi/src/modem/src/log.cpp
ringbellerpythonapi/src/modem/src/modem.cpp
ringbellerpythonapi/src/modem/src/utils.cpp
ringbellerpythonapi/src/wrapper/modemwrapper.cpp
ringbellerpythonapi/src/wrapper/modemwrapper.h
ringbellerpythonapi-0.0.2.dist-info/LICENSE
ringbellerpythonapi-0.0.2.dist-info/METADATA
ringbellerpythonapi-0.0.2.dist-info/WHEEL
ringbellerpythonapi-0.0.2.dist-info/top_level.txt
ringbellerpythonapi-0.0.2.dist-info/RECORD
