Metadata-Version: 2.1
Name: ringbellerpythonapi
Version: 0.0.2
Summary: Ringbeller IoT - Cellular library Python bindings
Home-page: UNKNOWN
Author: blueinsight
Author-email: dobreovidiu@yahoo.com
License: UNKNOWN
Platform: UNKNOWN
Classifier: Programming Language :: Python :: 3
Classifier: Operating System :: OS Independent
Requires-Python: >=3.6
